snappy_hx711/__init__.py
snappy_hx711/_version.py
snappy_hx711/hx711.py
snappy_hx711-1.0.0.dist-info/METADATA
snappy_hx711-1.0.0.dist-info/WHEEL
snappy_hx711-1.0.0.dist-info/top_level.txt
snappy_hx711-1.0.0.dist-info/RECORD
