Metadata-Version: 2.1
Name: snappy-hx711
Version: 1.0.0
Summary: Synapse SNAPpy library for HX711 Load Cell Amplifier/ADC
Home-page: https://github.com/tylercrumpton/snappy-hx711
Maintainer: Tyler Crumpton
Maintainer-email: tyler.crumpton@gmail.com
License: UNKNOWN
Platform: UNKNOWN
